{
  "collapse-filter": true,
  "search": "",
  "showTags": false,
  "showAttachments": false,
  "hideUnresolved": false,
  "showOrphans": true,
  "collapse-color-groups": false,
  "colorGroups": [
    {
      "query": "[\"type\":\"area_family\"]",
      "color": {
        "a": 1,
        "rgb": 14701138
      }
    },
    {
      "query": "[\"type\":\"area_note\"]",
      "color": {
        "a": 1,
        "rgb": 14725458
      }
    },
    {
      "query": "[\"type\":\"documentation_note\"]",
      "color": {
        "a": 1,
        "rgb": 11657298
      }
    },
    {
      "query": "[\"type\":\"source_note\"]",
      "color": {
        "a": 1,
        "rgb": 5431378
      }
    },
    {
      "query": "[\"type\":\"dev_resource_note\"]",
      "color": {
        "a": 1,
        "rgb": 5431473
      }
    },
    {
      "query": "[\"type\":\"link_note\"]",
      "color": {
        "a": 1,
        "rgb": 5419488
      }
    }
  ],
  "collapse-display": true,
  "showArrow": false,
  "textFadeMultiplier": 0,
  "nodeSizeMultiplier": 1,
  "lineSizeMultiplier": 1,
  "collapse-forces": false,
  "centerStrength": 0.484375,
  "repelStrength": 10.7291666666667,
  "linkStrength": 0.989583333333333,
  "linkDistance": 118,
  "scale": 0.6906395064657443,
  "close": false
}